LICENSE
README.md
setup.py
firebase_auth/__init__.py
firebase_auth/firebase_auth.py
micropython_firebase_auth.egg-info/PKG-INFO
micropython_firebase_auth.egg-info/SOURCES.txt
micropython_firebase_auth.egg-info/dependency_links.txt
micropython_firebase_auth.egg-info/top_level.txt