Metadata-Version: 2.1
Name: micropython-firebase-auth
Version: 1.0.6
Summary: Firebase Auth implementation for Micropython optimized for ESP32.
Home-page: https://github.com/WoolDoughnut310/micropython-firebase-auth
Author: WoolDoughnut310
Author-email: wooldoughnutspi@outlook.com
License: UNKNOWN
Platform: UNKNOWN
